humanizationdb/__init__.py
humanizationdb/core/__init__.py
humanizationdb/core/db.py
humanizationdb/core/db_entry.py
humanizationdb/utils/__init__.py
humanizationdb/utils/exceptions.py
humanizationdb-0.0.2.dist-info/LICENSE
humanizationdb-0.0.2.dist-info/METADATA
humanizationdb-0.0.2.dist-info/WHEEL
humanizationdb-0.0.2.dist-info/top_level.txt
humanizationdb-0.0.2.dist-info/RECORD
